agentverse_ai-0.3.0.dist-info/licenses/LICENSE
cookbook/__init__.py
cookbook/agent_concepts/__init__.py
cookbook/agent_concepts/async/__init__.py
cookbook/agent_concepts/async/basic.py
cookbook/agent_concepts/async/basic_stream.py
cookbook/agent_concepts/async/data_analyst.py
cookbook/agent_concepts/async/delay.py
cookbook/agent_concepts/async/gather_agents.py
cookbook/agent_concepts/async/reasoning.py
cookbook/agent_concepts/async/structured_output.py
cookbook/agent_concepts/async/tool_use.py
cookbook/agent_concepts/knowledge/__init__.py
cookbook/agent_concepts/knowledge/arxiv_kb.py
cookbook/agent_concepts/knowledge/combined_kb.py
cookbook/agent_concepts/knowledge/csv_kb.py
cookbook/agent_concepts/knowledge/csv_url_kb.py
cookbook/agent_concepts/knowledge/doc_kb.py
cookbook/agent_concepts/knowledge/docx_kb.py
cookbook/agent_concepts/knowledge/json_kb.py
cookbook/agent_concepts/knowledge/langchain_kb.py
cookbook/agent_concepts/knowledge/llamaindex_kb.py
cookbook/agent_concepts/knowledge/pdf_kb.py
cookbook/agent_concepts/knowledge/pdf_url_kb.py
cookbook/agent_concepts/knowledge/s3_pdf_kb.py
cookbook/agent_concepts/knowledge/s3_text_kb.py
cookbook/agent_concepts/knowledge/text_kb.py
cookbook/agent_concepts/knowledge/website_kb.py
cookbook/agent_concepts/knowledge/wikipedia_kb.py
cookbook/agent_concepts/knowledge/youtube_kb.py
cookbook/agent_concepts/knowledge/chunking/__init__.py
cookbook/agent_concepts/knowledge/chunking/agentic_chunking.py
cookbook/agent_concepts/knowledge/chunking/default.py
cookbook/agent_concepts/knowledge/chunking/document_chunking.py
cookbook/agent_concepts/knowledge/chunking/fixed_size_chunking.py
cookbook/agent_concepts/knowledge/chunking/recursive_chunking.py
cookbook/agent_concepts/knowledge/chunking/semantic_chunking.py
cookbook/agent_concepts/knowledge/custom/__init__.py
cookbook/agent_concepts/knowledge/custom/retriever.py
cookbook/agent_concepts/knowledge/embedders/__init__.py
cookbook/agent_concepts/knowledge/embedders/azure_embedder.py
agentverse_ai-0.3.0.dist-info/METADATA
agentverse_ai-0.3.0.dist-info/WHEEL
agentverse_ai-0.3.0.dist-info/top_level.txt
agentverse_ai-0.3.0.dist-info/RECORD
