Metadata-Version: 2.4
Name: agentverse-ai
Version: 0.3.0
Summary: A lightweight but powerful library for building (AI) multimodal agents with memory, tools, and knowledge.
Home-page: https://agentversai.app/
Author: Emmanuel Ebekue
Author-email: ebekue525@gmail.com
Classifier: Programming Language :: Python :: 3
Classifier: License :: OSI Approved :: MIT License
Classifier: Operating System :: OS Independent
Requires-Python: >=3.7
License-File: LICENSE
Requires-Dist: openai
Requires-Dist: duckduckgo-search
Requires-Dist: lancedb
Requires-Dist: tantivy
Requires-Dist: pypdf
Requires-Dist: yfinance
Dynamic: author
Dynamic: author-email
Dynamic: classifier
Dynamic: description
Dynamic: description-content-type
Dynamic: home-page
Dynamic: license-file
Dynamic: requires-dist
Dynamic: requires-python
Dynamic: summary
